LICENSE
README.md
flypper_sqlalchemy/__init__.py
flypper_sqlalchemy/py.typed
flypper_sqlalchemy/storage/__init__.py
flypper_sqlalchemy/storage/sqla.py
flypper_sqlalchemy-0.1.6.dist-info/LICENSE
flypper_sqlalchemy-0.1.6.dist-info/WHEEL
flypper_sqlalchemy-0.1.6.dist-info/METADATA
flypper_sqlalchemy-0.1.6.dist-info/RECORD
