Metadata-Version: 2.1
Name: flypper-sqlalchemy
Version: 0.1.6
Summary: Feature flags, with a GUI - SQL Alchemy backend
Home-page: https://github.com/nicoolas25/flypper-sqlalchemy
Author: Nicolas Zermati
Author-email: nicoolas25@gmail.com
Requires-Python: >=3.7,<4.0
Classifier: Programming Language :: Python :: 3
Classifier: Programming Language :: Python :: 3.10
Classifier: Programming Language :: Python :: 3.7
Classifier: Programming Language :: Python :: 3.8
Classifier: Programming Language :: Python :: 3.9
Requires-Dist: SQLAlchemy (>=1.3,<2.0)
Requires-Dist: flypper (>=0.1.6,<0.2.0)
Project-URL: Documentation, https://github.com/nicoolas25/flypper-sqlalchemy
Project-URL: Repository, https://github.com/nicoolas25/flypper-sqlalchemy
